Metadata-Version: 2.1
Name: zipline-live2
Version: 1.3.0.7.0
Summary: A backtester and live trader for financial algorithms.
Home-page: https://github.com/shlomikushchi/zipline-live2
Author: zipline-live community
Author-email: 
Maintainer: Shlomi Kushchi
License: Apache 2.0
Platform: UNKNOWN
Classifier: Development Status :: 3 - Alpha
Classifier: License :: OSI Approved :: Apache Software License
Classifier: Natural Language :: English
Classifier: Programming Language :: Python
Classifier: Programming Language :: Python :: 3.5
Classifier: Operating System :: OS Independent
Classifier: Intended Audience :: Science/Research
Classifier: Topic :: Office/Business :: Financial
Classifier: Topic :: Scientific/Engineering :: Information Analysis
Classifier: Topic :: System :: Distributed Computing
Requires-Dist: pip (>=7.1.0)
Requires-Dist: setuptools (>18.0)
Requires-Dist: Logbook (>=0.12.5)
Requires-Dist: pytz (>=2016.4)
Requires-Dist: numpy (>=1.11.1)
Requires-Dist: requests-file (>=1.4.1)
Requires-Dist: scipy (>=0.17.1)
Requires-Dist: pandas (<=0.22,>=0.18.1)
Requires-Dist: pandas-datareader (>=0.2.1)
Requires-Dist: patsy (>=0.4.0)
Requires-Dist: statsmodels (>=0.6.1)
Requires-Dist: python-dateutil (>=2.4.2)
Requires-Dist: six (>=1.10.0)
Requires-Dist: requests (>=2.9.1)
Requires-Dist: Cython (>=0.25.2)
Requires-Dist: cyordereddict (>=0.2.2)
Requires-Dist: bottleneck (>=1.0.0)
Requires-Dist: contextlib2 (>=0.4.0)
Requires-Dist: decorator (>=4.0.0)
Requires-Dist: networkx (<2.0,>=1.9.1)
Requires-Dist: numexpr (>=2.6.1)
Requires-Dist: bcolz (<1,>=0.12.1)
Requires-Dist: click (>=4.0.0)
Requires-Dist: toolz (>=0.8.2)
Requires-Dist: multipledispatch (>=0.4.8)
Requires-Dist: MarkupSafe (>=0.23)
Requires-Dist: Mako (>=1.0.1)
Requires-Dist: sqlalchemy (>=1.0.8)
Requires-Dist: alembic (>=0.7.7)
Requires-Dist: sortedcontainers (>=1.4.4)
Requires-Dist: intervaltree (>=2.1.0)
Requires-Dist: lru-dict (>=1.1.4)
Requires-Dist: empyrical (>=0.5.0)
Requires-Dist: tables (>=3.3.0)
Requires-Dist: trading-calendars (>=1.11.1)
Requires-Dist: IbPy2 (>=0.8.0)
Requires-Dist: polling (>=0.3.0)
Provides-Extra: all
Requires-Dist: coverage (==4.0.3) ; extra == 'all'
Requires-Dist: nose (==1.3.7) ; extra == 'all'
Requires-Dist: nose-parameterized (==0.5.0) ; extra == 'all'
Requires-Dist: nose-ignore-docstring (==0.2) ; extra == 'all'
Requires-Dist: termcolor (==1.1.0) ; extra == 'all'
Requires-Dist: nose-timer (==0.5.0) ; extra == 'all'
Requires-Dist: xlrd (==0.9.4) ; extra == 'all'
Requires-Dist: Jinja2 (==2.9.6) ; extra == 'all'
Requires-Dist: funcsigs (==1.0.2) ; extra == 'all'
Requires-Dist: Pygments (==2.0.2) ; extra == 'all'
Requires-Dist: alabaster (==0.7.6) ; extra == 'all'
Requires-Dist: babel (==1.3) ; extra == 'all'
Requires-Dist: docutils (==0.12) ; extra == 'all'
Requires-Dist: snowballstemmer (==1.2.0) ; extra == 'all'
Requires-Dist: sphinx-rtd-theme (==0.1.8) ; extra == 'all'
Requires-Dist: sphinx (==1.3.4) ; extra == 'all'
Requires-Dist: pbr (==1.10.0) ; extra == 'all'
Requires-Dist: mock (==2.0.0) ; extra == 'all'
Requires-Dist: testfixtures (==4.1.2) ; extra == 'all'
Requires-Dist: flake8 (==3.3.0) ; extra == 'all'
Requires-Dist: mccabe (==0.6.0) ; extra == 'all'
Requires-Dist: pycodestyle (==2.3.1) ; extra == 'all'
Requires-Dist: pyflakes (==1.5.0) ; extra == 'all'
Requires-Dist: pyandoc (==0.0.1) ; extra == 'all'
Requires-Dist: docopt (==0.6.2) ; extra == 'all'
Requires-Dist: numpydoc (==0.5) ; extra == 'all'
Requires-Dist: mistune (==0.7) ; extra == 'all'
Requires-Dist: tornado (==4.2.1) ; extra == 'all'
Requires-Dist: pyparsing (==2.0.3) ; extra == 'all'
Requires-Dist: cycler (==0.10.0) ; extra == 'all'
Requires-Dist: matplotlib (==1.5.3) ; extra == 'all'
Requires-Dist: Markdown (==2.6.2) ; extra == 'all'
Requires-Dist: futures (==3.0.5) ; extra == 'all'
Requires-Dist: requests-futures (==0.9.7) ; extra == 'all'
Requires-Dist: piprot (==0.9.6) ; extra == 'all'
Requires-Dist: responses (==0.9.0) ; extra == 'all'
Requires-Dist: pdbpp (==0.9.1) ; extra == 'all'
Requires-Dist: fancycompleter (==0.7) ; extra == 'all'
Requires-Dist: wmctrl (==0.3) ; extra == 'all'
Requires-Dist: TA-Lib (==0.4.9) ; extra == 'all'
Requires-Dist: alpaca-trade-api (==0.10) ; extra == 'all'
Provides-Extra: alpaca
Requires-Dist: alpaca-trade-api (==0.10) ; extra == 'alpaca'
Provides-Extra: dev
Requires-Dist: coverage (==4.0.3) ; extra == 'dev'
Requires-Dist: nose (==1.3.7) ; extra == 'dev'
Requires-Dist: nose-parameterized (==0.5.0) ; extra == 'dev'
Requires-Dist: nose-ignore-docstring (==0.2) ; extra == 'dev'
Requires-Dist: termcolor (==1.1.0) ; extra == 'dev'
Requires-Dist: nose-timer (==0.5.0) ; extra == 'dev'
Requires-Dist: xlrd (==0.9.4) ; extra == 'dev'
Requires-Dist: Jinja2 (==2.9.6) ; extra == 'dev'
Requires-Dist: funcsigs (==1.0.2) ; extra == 'dev'
Requires-Dist: Pygments (==2.0.2) ; extra == 'dev'
Requires-Dist: alabaster (==0.7.6) ; extra == 'dev'
Requires-Dist: babel (==1.3) ; extra == 'dev'
Requires-Dist: docutils (==0.12) ; extra == 'dev'
Requires-Dist: snowballstemmer (==1.2.0) ; extra == 'dev'
Requires-Dist: sphinx-rtd-theme (==0.1.8) ; extra == 'dev'
Requires-Dist: sphinx (==1.3.4) ; extra == 'dev'
Requires-Dist: pbr (==1.10.0) ; extra == 'dev'
Requires-Dist: mock (==2.0.0) ; extra == 'dev'
Requires-Dist: testfixtures (==4.1.2) ; extra == 'dev'
Requires-Dist: flake8 (==3.3.0) ; extra == 'dev'
Requires-Dist: mccabe (==0.6.0) ; extra == 'dev'
Requires-Dist: pycodestyle (==2.3.1) ; extra == 'dev'
Requires-Dist: pyflakes (==1.5.0) ; extra == 'dev'
Requires-Dist: pyandoc (==0.0.1) ; extra == 'dev'
Requires-Dist: docopt (==0.6.2) ; extra == 'dev'
Requires-Dist: numpydoc (==0.5) ; extra == 'dev'
Requires-Dist: mistune (==0.7) ; extra == 'dev'
Requires-Dist: tornado (==4.2.1) ; extra == 'dev'
Requires-Dist: pyparsing (==2.0.3) ; extra == 'dev'
Requires-Dist: cycler (==0.10.0) ; extra == 'dev'
Requires-Dist: matplotlib (==1.5.3) ; extra == 'dev'
Requires-Dist: Markdown (==2.6.2) ; extra == 'dev'
Requires-Dist: futures (==3.0.5) ; extra == 'dev'
Requires-Dist: requests-futures (==0.9.7) ; extra == 'dev'
Requires-Dist: piprot (==0.9.6) ; extra == 'dev'
Requires-Dist: responses (==0.9.0) ; extra == 'dev'
Requires-Dist: pdbpp (==0.9.1) ; extra == 'dev'
Requires-Dist: fancycompleter (==0.7) ; extra == 'dev'
Requires-Dist: wmctrl (==0.3) ; extra == 'dev'
Provides-Extra: talib
Requires-Dist: TA-Lib (==0.4.9) ; extra == 'talib'
